generate_dummyf/__init__.py
generate_dummyf/csv_generator.py
generate_dummyf/excel_generator.py
generate_dummyf/exceptions.py
generate_dummyf/generate.py
generate_dummyf/helper_functions.py
generate_dummyf/json_generator.py
generate_dummyf/txt_generator.py
generate_dummyf/validator.py
generate_dummyf/word_generator.py
generate_dummyf-1.1.4.dist-info/LICENSE
generate_dummyf-1.1.4.dist-info/METADATA
generate_dummyf-1.1.4.dist-info/WHEEL
generate_dummyf-1.1.4.dist-info/top_level.txt
generate_dummyf-1.1.4.dist-info/RECORD
