Metadata-Version: 2.1
Name: generate-dummyf
Version: 1.1.4
Summary: Generate different types (json, csv, excel, word, txt) of dummy files
Home-page: https://github.com/rubinakarkii/generate-dummyf
Author: Rubina Karki
Author-email: rubinakarki369@gmail.com
License: LICENSE
Platform: UNKNOWN
Requires-Dist: openpyxl
Requires-Dist: python-docx
